kscreen_switch/__init__.py
kscreen_switch/main.py
kscreen_switch-1.1.1.dist-info/LICENSE.txt
kscreen_switch-1.1.1.dist-info/METADATA
kscreen_switch-1.1.1.dist-info/WHEEL
kscreen_switch-1.1.1.dist-info/entry_points.txt
kscreen_switch-1.1.1.dist-info/top_level.txt
kscreen_switch-1.1.1.dist-info/RECORD
