Metadata-Version: 2.1
Name: kscreen-switch
Version: 1.1.1
Summary: A command-line utility to save, load, and manage monitor configuration profiles for KDE Plasma.
Author: Wojciech Banaś
License: MIT License
Project-URL: Homepage, https://github.com/fizista/kscreen-switch
Project-URL: Bug Tracker, https://github.com/fizista/kscreen-switch/issues
Keywords: kde,kscreen,display,monitor,profile,switch
Classifier: Development Status :: 5 - Production/Stable
Classifier: Environment :: X11 Applications :: KDE
Classifier: Intended Audience :: End Users/Desktop
Classifier: License :: OSI Approved :: MIT License
Classifier: Operating System :: POSIX :: Linux
Classifier: Programming Language :: Python :: 3
Classifier: Topic :: Desktop Environment :: K Desktop Environment (KDE)
Classifier: Topic :: Utilities
Requires-Python: >=3.7
License-File: LICENSE.txt
Provides-Extra: dev
Requires-Dist: twine ; extra == 'dev'
